config/judge_system_prompt.yaml
evals/nextjs/001-server-component.yaml
evals/nextjs/002-client-component.yaml
evals/nextjs/003-cookies.yaml
evals/nextjs/010-route-handlers.yaml
evals/nextjs/013-pathname-server.yaml
evals/nextjs/014-server-routing.yaml
evals/nextjs/018-use-router.yaml
evals/nextjs/020_no_use_effect.yaml
evals/nextjs/021-avoid-fetch-in-effect.yaml
evals/nextjs/022_prefer_server_actions.yaml
evals/nextjs/023_avoid_getserversideprops.yaml
evals/nextjs/024_avoid_redundant_usestate.yaml
evals/nextjs/025_no_async_client_components.yaml
evals/nextjs/026_no_serial_await.yaml
evals/nextjs/027-prefer-next-image.yaml
evals/nextjs/027_no_hooks_in_server_components.yaml
evals/nextjs/028-prefer-next-font.yaml
evals/nextjs/028_cookies_headers_context.yaml
evals/nextjs/029_no_catch_redirect.yaml
evals/nextjs/030_app_router_migration.yaml
evals/nextjs/031_no_non_serializable_props.yaml
evals/react/001_missing_useeffect_dependencies.yaml
evals/react/002_incorrect_event_handler.yaml
evals/react/003_missing_return_in_map.yaml
evals/react/004_async_useeffect.yaml
evals/react/005_direct_state_mutation.yaml
evals/react/006_index_as_key.yaml
evals/react/zustand_store_usage.yaml
evals/shadcn/001_cn_utility_function.yaml
evals/shadcn/002_css_variables.yaml
evals/shadcn/003_component_dependencies.yaml
evals/shadcn/004_path_aliases.yaml
evals/shadcn/005_client_directive.yaml
evals/shadcn/006_tailwind_config.yaml
evals/shadcn/007_components_json_config.yaml
evals/supabase/001_client_setup.yaml
evals/supabase/002_auth_context_setup.yaml
evals/supabase/003_auth_flow_implementation.yaml
evals/supabase/004_auth_flow_testing_WIP.yaml
evals/supabase/005_auth_google_oauth.yaml
evals/supabase/007_storage_client_setup.yaml
evals/supabase/008_storage_nextjs_config.yaml
evals/supabase/009_storage_image_upload.yaml
evals/supabase/010_security_rls_enabled.yaml
evals/supabase/011_security_rls_policies.yaml
evals/supabase/012_security_no_service_key_exposed.yaml
microevals-0.1.0.dist-info/licenses/LICENSE
microevals-0.1.0.dist-info/METADATA
microevals-0.1.0.dist-info/WHEEL
microevals-0.1.0.dist-info/entry_points.txt
microevals-0.1.0.dist-info/top_level.txt
microevals-0.1.0.dist-info/RECORD
