Metadata-Version: 2.4
Name: microevals
Version: 0.1.0
Summary: Automated evaluation framework for AI-generated code quality
Author-email: Design Arena <contact@designarena.ai>, Kamryn Ohly <kamryn@arcada.dev>
License: MIT
Project-URL: Homepage, https://github.com/Design-Arena/MicroEvals
Project-URL: Repository, https://github.com/Design-Arena/MicroEvals
Project-URL: Documentation, https://github.com/Design-Arena/MicroEvals#readme
Project-URL: Issues, https://github.com/Design-Arena/MicroEvals/issues
Keywords: evaluation,agents,ai,evals,design,benchmarks
Classifier: Programming Language :: Python :: 3
Classifier: Programming Language :: Python :: 3.8
Classifier: Programming Language :: Python :: 3.9
Classifier: Programming Language :: Python :: 3.10
Classifier: Programming Language :: Python :: 3.11
Classifier: Programming Language :: Python :: 3.12
Classifier: Programming Language :: Python :: 3.13
Classifier: License :: OSI Approved :: MIT License
Classifier: Operating System :: OS Independent
Requires-Python: >=3.8
License-File: LICENSE
Requires-Dist: requests>=2.31.0
Requires-Dist: pyyaml>=6.0
Requires-Dist: python-dotenv>=1.0.0
Dynamic: license-file
